common_things/IO_test.py
common_things/__init__.py
common_things/data_structures.py
common_things/random_anything.py
common_things-0.1.3.dist-info/METADATA
common_things-0.1.3.dist-info/WHEEL
common_things-0.1.3.dist-info/top_level.txt
common_things-0.1.3.dist-info/RECORD
