Metadata-Version: 2.4
Name: common_things
Version: 0.1.3
Summary: A toolkit.
Author-email: Gopa <36851252@qq.com>
Requires-Python: >=3.11
